lppls/data_loader.py
lppls/lppls.py
lppls/lppls_cmaes.py
lppls/lppls_lm.py
lppls/lppls_q.py
lppls/data/nasdaq_dotcom.csv
lppls-0.6.20.dist-info/METADATA
lppls-0.6.20.dist-info/WHEEL
lppls-0.6.20.dist-info/top_level.txt
lppls-0.6.20.dist-info/RECORD
