Metadata-Version: 2.1
Name: lppls
Version: 0.6.20
Summary: A Python module for fitting the LPPLS model to data.
Home-page: https://github.com/Boulder-Investment-Technologies/lppls
Author: Josh Nielsen
Author-email: josh@boulderinvestment.tech
Requires-Python: >=3.7
Requires-Dist: pandas
Requires-Dist: matplotlib
Requires-Dist: scipy
Requires-Dist: xarray
Requires-Dist: cma
Requires-Dist: tqdm
Requires-Dist: numba
